pandecay/__init__.py
pandecay/cli.py
pandecay/core/__init__.py
pandecay/core/analysis_engine.py
pandecay/core/configuration.py
pandecay/core/constants.py
pandecay/core/utils.py
pandecay-1.1.0.dist-info/licenses/LICENSE
pandecay-1.1.0.dist-info/METADATA
pandecay-1.1.0.dist-info/WHEEL
pandecay-1.1.0.dist-info/entry_points.txt
pandecay-1.1.0.dist-info/top_level.txt
pandecay-1.1.0.dist-info/RECORD
