Metadata-Version: 2.4
Name: pandecay
Version: 1.1.0
Summary: Phylogenetic Analysis using Decay Indices
Author-email: James McInerney <mcinerney.james+panGPT@gmail.com>
License: MIT License
Project-URL: Homepage, https://github.com/mol-evol/panDecay
Project-URL: Documentation, https://github.com/mol-evol/panDecay#readme
Project-URL: Repository, https://github.com/mol-evol/panDecay
Project-URL: Bug Reports, https://github.com/mol-evol/panDecay/issues
Keywords: phylogenetics,bioinformatics,decay-indices,bremer-support,maximum-likelihood,bayesian,parsimony
Classifier: Development Status :: 4 - Beta
Classifier: Intended Audience :: Science/Research
Classifier: Topic :: Scientific/Engineering :: Bio-Informatics
Classifier: License :: OSI Approved :: MIT License
Classifier: Programming Language :: Python :: 3
Classifier: Programming Language :: Python :: 3.8
Classifier: Programming Language :: Python :: 3.9
Classifier: Programming Language :: Python :: 3.10
Classifier: Programming Language :: Python :: 3.11
Classifier: Programming Language :: Python :: 3.12
Classifier: Operating System :: OS Independent
Requires-Python: >=3.8
License-File: LICENSE
Requires-Dist: biopython>=1.79
Requires-Dist: numpy>=1.20.0
Requires-Dist: ete3>=3.1.3
Provides-Extra: visualization
Requires-Dist: matplotlib>=3.5.0; extra == "visualization"
Requires-Dist: seaborn>=0.11.0; extra == "visualization"
Provides-Extra: dev
Requires-Dist: pytest>=6.0; extra == "dev"
Requires-Dist: pytest-cov; extra == "dev"
Requires-Dist: black; extra == "dev"
Requires-Dist: flake8; extra == "dev"
Dynamic: license-file
